Metadata-Version: 1.1
Name: Singkatan
Version: 0.1.2
Summary: A simple converter for slang word in indonesian into actual word
Home-page: https://github.com/khumam/Singkatan
Author: Khoerul Umam
Author-email: id.khoerulumam@gmail.com
License: MIT
Keywords: slang converter word in indonesian
Platform: UNKNOWN
Classifier: Development Status :: 4 - Beta
Classifier: Intended Audience :: Science/Research
Classifier: Intended Audience :: Information Technology
Classifier: License :: OSI Approved :: MIT License
Classifier: Operating System :: POSIX :: Linux
Classifier: Programming Language :: Python :: 2
Classifier: Programming Language :: Python :: 2.7
Classifier: Programming Language :: Python :: 3
Classifier: Programming Language :: Python :: 3.4
Classifier: Programming Language :: Python :: 3.5
